pytest_blender/__init__.py
pytest_blender/__main__.py
pytest_blender/options.py
pytest_blender/plugin.py
pytest_blender/run_pytest.py
pytest_blender/utils.py
pytest_blender-3.0.7.dist-info/LICENSE
pytest_blender-3.0.7.dist-info/METADATA
pytest_blender-3.0.7.dist-info/WHEEL
pytest_blender-3.0.7.dist-info/entry_points.txt
pytest_blender-3.0.7.dist-info/top_level.txt
pytest_blender-3.0.7.dist-info/RECORD
