Metadata-Version: 2.1
Name: pytest-blender
Version: 3.0.7
Summary: Blender Pytest plugin.
Home-page: https://github.com/mondeja/pytest-blender
Author: Álvaro Mondéjar Rubio
Author-email: mondejar1994@gmail.com
License: BSD-3-Clause
Project-URL: Documentation, https://github.com/mondeja/pytest-blender#documentation
Project-URL: GitHub Project, https://github.com/mondeja/pytest-blender
Project-URL: Issue Tracker, https://github.com/mondeja/pytest-blender/issues
Project-URL: Changelog, https://github.com/mondeja/pytest-blender/releases
Classifier: Framework :: Pytest
Classifier: License :: OSI Approved :: BSD License
Classifier: Programming Language :: Python
Classifier: Programming Language :: Python :: 3
Classifier: Programming Language :: Python :: 3 :: Only
Classifier: Programming Language :: Python :: 3.7
Classifier: Programming Language :: Python :: 3.8
Classifier: Programming Language :: Python :: 3.9
Classifier: Programming Language :: Python :: 3.10
Classifier: Programming Language :: Python :: 3.11
Classifier: Programming Language :: Python :: 3.12
Requires-Python: >=3.7
License-File: LICENSE
Requires-Dist: pytest
Provides-Extra: dev
Requires-Dist: pytest-cov; extra == "dev"
Provides-Extra: test
Requires-Dist: pytest-cov; extra == "test"
